colorana/__init__.py
colorana/main.py
colorana-0.0.1.dist-info/METADATA
colorana-0.0.1.dist-info/WHEEL
colorana-0.0.1.dist-info/licenses/LICENSE
colorana-0.0.1.dist-info/RECORD
